syndicate/__init__.py
syndicate/mini/__init__.py
syndicate/mini/core.py
syndicate/mini/protocol.py
syndicate/mini/url.py
mini_syndicate-0.0.7.dist-info/METADATA
mini_syndicate-0.0.7.dist-info/WHEEL
mini_syndicate-0.0.7.dist-info/top_level.txt
mini_syndicate-0.0.7.dist-info/RECORD
