Metadata-Version: 2.1
Name: mini-syndicate
Version: 0.0.7
Summary: Syndicate-like library for integrating Python with the Syndicate ecosystem
Home-page: https://github.com/syndicate-lang/mini-syndicate-py
Author: Tony Garnock-Jones
Author-email: tonyg@leastfixedpoint.com
License: GNU General Public License v3 or later (GPLv3+)
Platform: UNKNOWN
Classifier: Development Status :: 3 - Alpha
Classifier: Intended Audience :: Developers
Classifier: Topic :: Software Development :: Libraries :: Python Modules
Classifier: License :: OSI Approved :: GNU General Public License v3 or later (GPLv3+)
Classifier: Programming Language :: Python :: 3
Requires-Python: >=3.6, <4
Requires-Dist: websockets
Requires-Dist: preserves
